{
  "forge_marker": 1,
  "defaults": {
    "transform": "forge:default-block"
  },
  "variants": {
    "type": {
      "large": {
        "model": "cookingforblockheads:fridge_large_static"
      }
    },
    "facing": {
      "west": {
        "y": -90
      },
      "east": {
        "y": 90
      },
      "north": {
      },
      "south": {
        "y": 180
      }
    },
    "flipped": {
      "true": {
        "submodel": {
          "hinge": {
            "model": "cookingforblockheads:fridge_large_hinge_right"
          }
        }
      },
      "false": {
        "submodel": {
          "hinge": {
            "model": "cookingforblockheads:fridge_large_hinge_left"
          }
        }
      }
    }
  }
}